[{
    "label": "Text Left / Media Right",
    "value": "textLeft",

    "settings": {
        "grid": "_layouts/grids/splitNormal",
        "container": "container @container"
    }
},

{
    "label": "Text Right / Media Left",
    "value": "textRight",

    "settings": {
        "grid": "_layouts/grids/splitReverse",
        "container": "container @container"
    }
},

{
    "label": "Text Above Media",
    "value": "textAbove",

    "settings": {
        "grid": "_layouts/grids/stacked",
        "container": "container @container"
    }
}]