[
    {% if object.type ?? null == 'fragment' %}{ "label": "Use Setting from Fragment", "value": "FRAGMENT" },{% endif %}

    {
        "label": "Base (Page Background Visible)",
        "value": "base",
        "docs": {
            "tooltip" : ""
        },
        "settings": {},
        "inputs": [
            {{ block( 'inputSpacerAbove', '_config/_selectplus_virtual_fields' ) }},
            {{ block( 'inputSpacerBelow', '_config/_selectplus_virtual_fields' ) }},
            {{ block( 'inputContainer',   '_config/_selectplus_virtual_fields' ) }},
            {{ block( 'inputBlockBottom', '_config/_selectplus_virtual_fields' ) }}
        ]
    }

   ,{
        "label": "White (Light)",
        "value": "light",
        "docs": {
            "tooltip" : ""
        },
        "settings": {},
        "inputs": [
            {{ block( 'inputSpacerAbove', '_config/_selectplus_virtual_fields' ) }},
            {{ block( 'inputSpacerBelow', '_config/_selectplus_virtual_fields' ) }},
            {{ block( 'inputContainer',   '_config/_selectplus_virtual_fields' ) }},
            {{ block( 'inputBlockBottom', '_config/_selectplus_virtual_fields' ) }},
            {{ block( 'inputCanvasCoverage', '_config/_selectplus_virtual_fields' ) }}
        ]
    }

   ,{
        "label": "Accent (Dark)",
        "value": "accent",
        "docs": {
            "tooltip" : ""
        },
        "settings": {},
        "inputs": [
            {{ block( 'inputSpacerAbove', '_config/_selectplus_virtual_fields' ) }},
            {{ block( 'inputSpacerBelow', '_config/_selectplus_virtual_fields' ) }},
            {{ block( 'inputContainer',   '_config/_selectplus_virtual_fields' ) }},
            {{ block( 'inputBlockBottom', '_config/_selectplus_virtual_fields' ) }},

            {{ block( 'inputCanvasCoverage', '_config/_selectplus_virtual_fields' ) }}
        ]
    }

   ,{
        "label": "Inherit from Block Above",
        "value": "INHERIT",
        "docs": {
            "tooltip" : ""
        },
        "settings": {},
        "inputs": [
            {{ block( 'inputSpacerAbove', '_config/_selectplus_virtual_fields' ) }},
            {{ block( 'inputSpacerBelow', '_config/_selectplus_virtual_fields' ) }},
            {{ block( 'inputContainer',   '_config/_selectplus_virtual_fields' ) }},
            {{ block( 'inputBlockBottom', '_config/_selectplus_virtual_fields' ) }}
        ]

    }
]